tql/__init__.py
truston_query_language-0.0.1.17.dist-info/METADATA
truston_query_language-0.0.1.17.dist-info/WHEEL
truston_query_language-0.0.1.17.dist-info/top_level.txt
truston_query_language-0.0.1.17.dist-info/RECORD
